newdao_hello_tea/__init__.py
newdao_hello_tea/main.py
newdao_hello_tea-2.0.0.dist-info/METADATA
newdao_hello_tea-2.0.0.dist-info/WHEEL
newdao_hello_tea-2.0.0.dist-info/entry_points.txt
newdao_hello_tea-2.0.0.dist-info/top_level.txt
newdao_hello_tea-2.0.0.dist-info/RECORD
